AIFunction/__init__.py
AIFunction/main.py
AIFunction/modules/__init__.py
AIFunction/modules/web/__init__.py
AIFunction/modules/web/OpenAI/OpenAI.py
AIFunction/modules/web/OpenAI/__init__.py
AIFunction-1.0.9.dist-info/METADATA
AIFunction-1.0.9.dist-info/WHEEL
AIFunction-1.0.9.dist-info/top_level.txt
AIFunction-1.0.9.dist-info/RECORD
