Metadata-Version: 2.1
Name: AIFunction
Version: 1.0.9
Summary: Generate realtime AI Functions!
Home-page: https://github.com/nekumelon/AIFunction
Author: nekumelon
Author-email: nekumelon@gmail.com
Classifier: Programming Language :: Python :: 3
Classifier: License :: OSI Approved :: MIT License
Classifier: Operating System :: OS Independent
Requires-Python: >=3.6
